treemendous/__init__.py
treemendous/basic/__init__.py
treemendous/basic/avl.py
treemendous/basic/avl_earliest.py
treemendous/basic/base.py
treemendous/basic/boundary.py
treemendous/basic/segment.py
treemendous/cpp/__init__.py
treemendous/cpp/boundary.cpp
treemendous/cpp/boundary_bindings.cpp
treemendous/cpp/boundary_ic.cpp
treemendous/cpp/boundary.cpython-312-x86_64-linux-gnu.so
treemendous-0.1.0.dist-info/LICENSE
treemendous-0.1.0.dist-info/METADATA
treemendous-0.1.0.dist-info/WHEEL
treemendous-0.1.0.dist-info/RECORD
