Metadata-Version: 2.1
Name: treemendous
Version: 0.1.0
Summary: Exploring a diverse collection of interval tree implementations across multiple programming languages to identify the most efficient configurations for varied use cases, such as optimizing for query speed, memory usage, or dynamic updates.
License: BSD 3-Clause License
Author: Joseph Cox
Author-email: joseph@codensity.io
Requires-Python: >=3.9,<4.0
Classifier: License :: Other/Proprietary License
Classifier: Programming Language :: Python :: 3
Classifier: Programming Language :: Python :: 3.9
Classifier: Programming Language :: Python :: 3.10
Classifier: Programming Language :: Python :: 3.11
Classifier: Programming Language :: Python :: 3.12
Classifier: Programming Language :: Python :: 3.13
Requires-Dist: sortedcollections (>=2.1.0,<3.0.0)
Requires-Dist: sortedcontainers (>=2.4.0,<3.0.0)
